{
  "version": "v87-2026-07-16",
  "note": "spec-v7 section 3.2: hand-curated patient-phrasing -> tile id table. Each entry maps patient-mental-model phrases (and, from the v8/v9 plain-language-search batches, clinical abbreviations, eponym aliases, and canonical-intent phrases) to a single existing tile. Audience is the primary audience the entry serves; the matcher deprioritizes (does not hide) entries when the user has selected a different chip. Every phrase is lowercase; every tile id is an existing catalog tile (guarded by test/unit/synonyms-catalog.test.js). Adding a new phrase is a one-line PR.",
  "entries": [
    { "phrases": ["denied", "denial letter", "they denied it", "insurance said no", "appeal", "write an appeal", "appeal my claim", "appeal letter", "appeal a denial"],
      "tile": "appeal-letter", "audience": "patients" },
    { "phrases": ["my labs", "my lab results", "lab results", "blood work", "my labs came back", "my labs are weird", "what does my lab mean", "explain my labs", "interpret my labs", "read my labs"],
      "tile": "lab-interpret", "audience": "patients" },
    { "phrases": ["request my records", "release of information", "roi request", "hipaa request", "get my medical records", "right of access"],
      "tile": "hipaa-roa", "audience": "patients" },
    { "phrases": ["hipaa authorization", "share my records", "authorize records release"],
      "tile": "hipaa-auth", "audience": "patients" },
    { "phrases": ["bmi", "body mass index", "what is my bmi"],
      "tile": "bmi", "audience": "clinicians" },
    { "phrases": ["egfr", "ckd-epi", "kidney function", "creatinine clearance", "estimate kidney function", "estimating gfr", "estimated gfr", "renal function", "estimate gfr"],
      "tile": "egfr", "audience": "clinicians" },
    { "phrases": ["qtc", "corrected qt", "qt interval"],
      "tile": "qtc", "audience": "clinicians" },
    { "phrases": ["unit converter", "convert units", "mg to mmol", "lb to kg"],
      "tile": "unit-converter-v4", "audience": "patients" },
    { "phrases": ["prior auth", "prior authorization", "preauth", "preauthorization", "pa packet", "pa linter", "pa checker", "packet check", "pa checklist", "utilization management", "um packet", "denial prevention"],
      "tile": "pa-lint", "audience": "billers" },

    { "phrases": ["afib", "a fib", "atrial fibrillation", "stroke risk in afib", "afib stroke risk", "stroke risk atrial fibrillation", "af stroke risk", "cha2ds2", "cha2ds2 vasc", "chads2 vasc", "chadsvasc", "chads vasc", "anticoagulation in afib"],
      "tile": "chads", "audience": "clinicians" },
    { "phrases": ["bleeding risk on anticoagulation", "has bled", "hasbled", "bleeding risk warfarin", "anticoagulation bleeding risk", "afib bleeding risk"],
      "tile": "hasbled", "audience": "clinicians" },
    { "phrases": ["orbit bleeding score", "orbit score"],
      "tile": "orbit-bleeding", "audience": "clinicians" },
    { "phrases": ["pe risk", "pulmonary embolism probability", "wells score for pe", "wells pe"],
      "tile": "wells-pe", "audience": "clinicians" },
    { "phrases": ["dvt risk", "wells score for dvt", "wells dvt", "leg clot probability"],
      "tile": "wells-dvt", "audience": "clinicians" },
    { "phrases": ["perc rule", "rule out pe", "pe rule out"],
      "tile": "perc", "audience": "clinicians" },
    { "phrases": ["pneumonia severity", "curb 65", "curb65", "admit for pneumonia"],
      "tile": "curb-65", "audience": "clinicians" },
    { "phrases": ["strep throat score", "centor", "sore throat score"],
      "tile": "centor", "audience": "clinicians" },
    { "phrases": ["early warning score", "news 2", "news2", "deterioration score"],
      "tile": "news2", "audience": "clinicians" },
    { "phrases": ["modified early warning score", "mews"],
      "tile": "mews", "audience": "clinicians" },
    { "phrases": ["qsofa", "sofa score", "sepsis organ failure", "sepsis screen", "sepsis screening"],
      "tile": "qsofa-sofa", "audience": "clinicians" },
    { "phrases": ["rass", "sedation scale", "sedation depth", "richmond agitation", "agitation sedation scale"],
      "tile": "rass", "audience": "clinicians" },
    { "phrases": ["heparin drip", "heparin gtt", "heparin infusion", "heparin nomogram"],
      "tile": "heparin-nomogram", "audience": "clinicians" },
    { "phrases": ["sirs criteria", "systemic inflammatory response"],
      "tile": "sirs", "audience": "clinicians" },
    { "phrases": ["chest pain score", "heart score", "acs risk chest pain"],
      "tile": "heart", "audience": "clinicians" },
    { "phrases": ["timi score", "timi risk"],
      "tile": "timi", "audience": "clinicians" },
    { "phrases": ["grace score", "grace acs"],
      "tile": "grace", "audience": "clinicians" },
    { "phrases": ["vte prophylaxis risk", "padua score", "padua prediction"],
      "tile": "padua", "audience": "clinicians" },
    { "phrases": ["gi bleed score", "upper gi bleed risk", "blatchford", "glasgow blatchford"],
      "tile": "glasgow-blatchford", "audience": "clinicians" },
    { "phrases": ["pancreatitis severity", "ranson criteria", "bisap"],
      "tile": "ranson-bisap", "audience": "clinicians" },
    { "phrases": ["liver disease severity", "meld score", "meld na", "meld sodium"],
      "tile": "meld-na", "audience": "clinicians" },
    { "phrases": ["child pugh", "child pugh score", "cirrhosis severity"],
      "tile": "meld-childpugh", "audience": "clinicians" },
    { "phrases": ["liver fibrosis score", "fib 4", "fib4 index"],
      "tile": "fib4", "audience": "clinicians" },
    { "phrases": ["apri score", "ast platelet ratio"],
      "tile": "apri", "audience": "clinicians" },
    { "phrases": ["alcoholic hepatitis severity", "maddrey", "discriminant function", "lille score"],
      "tile": "maddrey-lille", "audience": "clinicians" },
    { "phrases": ["dka", "diabetic ketoacidosis", "hhs", "hyperosmolar hyperglycemic"],
      "tile": "dka-hhs", "audience": "clinicians" },
    { "phrases": ["alcohol withdrawal", "ciwa", "ciwa ar"],
      "tile": "ciwa", "audience": "clinicians" },
    { "phrases": ["opioid withdrawal", "cows score", "clinical opiate withdrawal"],
      "tile": "cows", "audience": "clinicians" },
    { "phrases": ["pressure ulcer risk", "pressure injury risk", "braden score", "pressure injuries", "skin breakdown risk", "assess for pressure injury"],
      "tile": "braden", "audience": "clinicians" },
    { "phrases": ["fall risk score", "morse fall scale", "morse falls", "risk of falling", "falls assessment", "fall risk assessment"],
      "tile": "morse-falls", "audience": "clinicians" },
    { "phrases": ["hendrich", "hendrich ii", "hendrich fall risk model"],
      "tile": "hendrich-ii", "audience": "clinicians" },
    { "phrases": ["stroke severity", "nih stroke scale", "nihss"],
      "tile": "nihss", "audience": "clinicians" },
    { "phrases": ["coma scale", "glasgow coma scale", "gcs"],
      "tile": "gcs", "audience": "clinicians" },
    { "phrases": ["newborn apgar", "apgar score"],
      "tile": "apgar", "audience": "clinicians" },
    { "phrases": ["cervix favorable for induction", "bishop score", "induction readiness"],
      "tile": "bishop", "audience": "clinicians" },
    { "phrases": ["anion gap", "high anion gap"],
      "tile": "anion-gap", "audience": "clinicians" },
    { "phrases": ["corrected calcium", "calcium for albumin", "albumin corrected calcium"],
      "tile": "corrected-calcium", "audience": "clinicians" },
    { "phrases": ["expected pco2 metabolic acidosis", "winters formula", "respiratory compensation", "metabolic acidosis compensation"],
      "tile": "winters", "audience": "clinicians" },
    { "phrases": ["osmolar gap", "osmolal gap", "toxic alcohol gap", "serum osmolality", "calculated osmolality", "serum osmolality calculation"],
      "tile": "osmolal-gap", "audience": "clinicians" },
    { "phrases": ["aki staging", "acute kidney injury staging", "kdigo aki", "kdigo staging"],
      "tile": "kdigo-aki", "audience": "clinicians" },
    { "phrases": ["hit score", "4t score", "4ts score", "heparin induced thrombocytopenia", "heparin thrombocytopenia"],
      "tile": "four-ts", "audience": "clinicians" },
    { "phrases": ["gestational diabetes screen", "gdm screen", "gdm criteria", "gestational diabetes criteria"],
      "tile": "iadpsg", "audience": "clinicians" },
    { "phrases": ["when to transfuse", "transfusion threshold", "transfusion trigger", "hemoglobin transfusion trigger", "hgb transfusion threshold", "restrictive transfusion", "transfusion cutoff", "when should i transfuse for anemia"],
      "tile": "transfusion-threshold", "audience": "clinicians" },
    { "phrases": ["a a gradient", "alveolar arterial gradient", "aa gradient"],
      "tile": "aa-gradient", "audience": "clinicians" },
    { "phrases": ["cockcroft gault", "creatinine clearance formula", "crcl"],
      "tile": "cockcroft-gault", "audience": "clinicians" },
    { "phrases": ["cardiovascular risk", "ascvd risk", "10 year heart risk", "atherosclerotic risk"],
      "tile": "ascvd", "audience": "clinicians" },
    { "phrases": ["framingham risk", "framingham cardiovascular"],
      "tile": "framingham-cvd", "audience": "clinicians" },
    { "phrases": ["morphine equivalents", "mme", "opioid conversion", "morphine milligram equivalents", "convert opioids", "opioid equivalent", "opioid dose conversion"],
      "tile": "opioid-mme", "audience": "clinicians" },
    { "phrases": ["steroid conversion", "convert steroids", "steroid equivalent", "prednisone equivalent", "glucocorticoid conversion"],
      "tile": "steroid-equiv", "audience": "clinicians" },
    { "phrases": ["mean arterial pressure", "map calculation"],
      "tile": "map", "audience": "clinicians" },
    { "phrases": ["corrected phenytoin", "free phenytoin", "albumin corrected phenytoin"],
      "tile": "corrected-phenytoin", "audience": "clinicians" },
    { "phrases": ["shock index"],
      "tile": "shock-index", "audience": "clinicians" },
    { "phrases": ["transtubular potassium gradient", "ttkg"],
      "tile": "ttkg", "audience": "clinicians" },
    { "phrases": ["fractional excretion of sodium", "fena", "fractional excretion of urea", "feurea"],
      "tile": "fena-feurea", "audience": "clinicians" },
    { "phrases": ["estimated average glucose", "a1c to average glucose", "eag"],
      "tile": "eag-a1c", "audience": "clinicians" },
    { "phrases": ["pediatric fluid deficit", "dehydration fluid deficit"],
      "tile": "peds-fluid-deficit", "audience": "clinicians" },
    { "phrases": ["sodium correction rate", "how fast to correct sodium", "safe sodium correction rate", "hyponatremia correction rate", "sodium overcorrection"],
      "tile": "sodium-correction", "audience": "clinicians" },
    { "phrases": ["corrected sodium for glucose", "sodium correction for hyperglycemia", "hyperglycemia sodium"],
      "tile": "corrected-sodium", "audience": "clinicians" },
    { "phrases": ["burn fluid resuscitation", "parkland formula", "fluid for burns"],
      "tile": "burn-fluid", "audience": "clinicians" },
    { "phrases": ["depression screen", "phq 9", "phq9"],
      "tile": "phq9", "audience": "clinicians" },
    { "phrases": ["anxiety screen", "gad 7", "gad7"],
      "tile": "gad7", "audience": "clinicians" },
    { "phrases": ["alcohol use screen", "audit c", "auditc"],
      "tile": "auditc", "audience": "clinicians" },
    { "phrases": ["cage questionnaire", "cage alcohol"],
      "tile": "cage", "audience": "clinicians" },
    { "phrases": ["potassium deficit", "potassium replacement"],
      "tile": "potassium-deficit", "audience": "clinicians" },
    { "phrases": ["magnesium replacement", "magnesium repletion"],
      "tile": "magnesium-replacement", "audience": "clinicians" },
    { "phrases": ["serotonin syndrome", "serotonin toxicity", "hunter criteria"],
      "tile": "serotonin-toxicity", "audience": "clinicians" },
    { "phrases": ["copd admission risk", "when to admit copd", "ottawa copd"],
      "tile": "ottawa-copd", "audience": "clinicians" },
    { "phrases": ["frailty score", "frailty index", "frailty assessment"],
      "tile": "sof-frailty-index", "audience": "clinicians" },
    { "phrases": ["groningen frailty"],
      "tile": "groningen-frailty-indicator", "audience": "clinicians" },
    { "phrases": ["pediatric gfr", "gfr in kids", "schwartz equation", "bedside schwartz", "child kidney function"],
      "tile": "schwartz-egfr", "audience": "clinicians" },
    { "phrases": ["post op nausea risk", "post op nausea", "postop nausea", "postoperative nausea risk", "ponv risk score", "nausea risk after surgery", "apfel score"],
      "tile": "apfel", "audience": "clinicians" },
    { "phrases": ["pre op cardiac risk", "preop cardiac risk", "preoperative cardiac risk", "cardiac risk before surgery", "revised cardiac risk index", "lee index"],
      "tile": "rcri", "audience": "clinicians" },
    { "phrases": ["nec fasc", "necrotizing fasciitis", "cellulitis vs nec fasc", "necrotizing soft tissue infection", "lrinec"],
      "tile": "lrinec", "audience": "clinicians" },
    { "phrases": ["phlebitis scale", "phlebitis score", "iv site phlebitis", "visual infusion phlebitis", "vip score", "iv phlebitis grade"],
      "tile": "vip-extravasation", "audience": "clinicians" },
    { "phrases": ["c diff severity", "cdiff severity", "c diff severity score", "clostridium difficile severity", "atlas c diff"],
      "tile": "atlas-cdi", "audience": "clinicians" },
    { "phrases": ["insulin sliding scale", "sliding scale insulin", "sliding scale", "correction dose insulin", "insulin sensitivity factor"],
      "tile": "insulin-correction", "audience": "clinicians" },
    { "phrases": ["fast dementia staging", "fast scale dementia", "functional assessment staging", "reisberg fast", "dementia hospice eligibility", "fast stage 7a"],
      "tile": "fast-dementia", "audience": "clinicians" },
    { "phrases": ["global deterioration scale", "reisberg gds", "gds dementia stage", "dementia stage 1 to 7", "seven stages of dementia"],
      "tile": "global-deterioration-scale", "audience": "clinicians" },
    { "phrases": ["benzodiazepine equivalence", "benzo equivalent dose", "benzo conversion", "diazepam equivalent", "lorazepam to diazepam", "clonazepam to diazepam", "benzodiazepine taper conversion"],
      "tile": "benzodiazepine-equivalence", "audience": "clinicians" },
    { "phrases": ["seddon sunderland", "nerve injury classification", "nerve injury grade", "neurapraxia axonotmesis neurotmesis", "sunderland grade", "peripheral nerve injury grading"],
      "tile": "seddon-sunderland", "audience": "clinicians" },
    { "phrases": ["return to play", "return to sport", "return to play protocol", "concussion return to play", "graduated return to sport", "rts strategy", "return to sport steps", "concussion return to sport"],
      "tile": "concussion-rts", "audience": "clinicians" },
    { "phrases": ["cosyntropin stimulation test", "acth stimulation test", "cosyntropin test", "cortrosyn test", "adrenal insufficiency test", "short synacthen test", "peak cortisol threshold"],
      "tile": "cosyntropin-stim", "audience": "clinicians" },
    { "phrases": ["rule of 6s", "rule of sixes", "fistula maturation", "avf maturation", "arteriovenous fistula maturation", "fistula rule of 6", "dialysis fistula maturation"],
      "tile": "avf-rule-of-6s", "audience": "clinicians" },
    { "phrases": ["diabetic retinopathy severity", "diabetic retinopathy grading", "icdr scale", "retinopathy grade", "npdr severity", "proliferative retinopathy", "nonproliferative diabetic retinopathy"],
      "tile": "icdr-retinopathy", "audience": "clinicians" },
    { "phrases": ["instability severity index score", "isis shoulder", "shoulder instability recurrence", "shoulder dislocation recurrence risk", "bankart recurrence risk", "arthroscopic bankart vs latarjet"],
      "tile": "isis-shoulder", "audience": "clinicians" },
    { "phrases": ["anaphylaxis grade", "anaphylaxis severity grading", "ring messmer classification", "anaphylactic reaction severity", "perioperative anaphylaxis grade", "hypersensitivity reaction grade"],
      "tile": "anaphylaxis-grade", "audience": "clinicians" },
    { "phrases": ["thyroid nodule malignancy risk", "thyroid nodule risk", "ti-rads", "tirads", "thyroid nodule ultrasound", "thyroid ultrasound risk", "thyroid nodule classification"],
      "tile": "acr-tirads", "audience": "clinicians" },
    { "phrases": ["dexamethasone suppression test", "cushing screening", "cushing syndrome screen", "overnight dexamethasone test", "1mg dexamethasone suppression", "cortisol suppression test", "autonomous cortisol secretion"],
      "tile": "dexamethasone-suppression", "audience": "clinicians" },
    { "phrases": ["cytokine release syndrome grade", "crs grading", "astct crs grade", "car t cytokine release", "cytokine release syndrome severity", "immune effector cell crs", "car-t toxicity grade"],
      "tile": "crs-grade", "audience": "clinicians" },
    { "phrases": ["icans grade", "icans grading", "car t neurotoxicity", "immune effector cell neurotoxicity", "ice score neurotoxicity", "astct icans grade", "car-t neurotoxicity grade"],
      "tile": "icans-grade", "audience": "clinicians" },
    { "phrases": ["diabetic macular edema severity", "dme severity", "macular edema grading", "diabetic macular edema grade", "center involving dme", "clinically significant macular edema"],
      "tile": "dme-severity", "audience": "clinicians" },
    { "phrases": ["return to learn", "return to school concussion", "concussion return to learn", "graduated return to learn", "concussion school accommodations", "rtl strategy"],
      "tile": "concussion-rtl", "audience": "clinicians" },
    { "phrases": ["graft versus host disease grading", "gvhd grade", "acute gvhd grade", "gvhd severity", "glucksberg gvhd", "gvhd staging", "acute graft versus host disease"],
      "tile": "gvhd-grade", "audience": "clinicians" },
    { "phrases": ["acute cholangitis severity", "cholangitis grade", "cholangitis severity grade", "tokyo guidelines cholangitis", "tg18 cholangitis", "ascending cholangitis severity", "biliary sepsis grade"],
      "tile": "cholangitis-severity", "audience": "clinicians" },
    { "phrases": ["acute cholecystitis severity", "cholecystitis grade", "cholecystitis severity grade", "tokyo guidelines cholecystitis", "tg18 cholecystitis", "gallbladder infection severity", "gangrenous cholecystitis grade"],
      "tile": "cholecystitis-severity", "audience": "clinicians" },
    { "phrases": ["acute cholangitis diagnosis", "cholangitis diagnostic criteria", "tokyo guidelines cholangitis diagnosis", "tg18 cholangitis criteria", "diagnose cholangitis", "charcot triad cholangitis", "reynolds pentad"],
      "tile": "cholangitis-diagnosis", "audience": "clinicians" },
    { "phrases": ["acute cholecystitis diagnosis", "cholecystitis diagnostic criteria", "tokyo guidelines cholecystitis diagnosis", "tg18 cholecystitis criteria", "diagnose cholecystitis", "murphy sign cholecystitis", "gallbladder inflammation diagnosis"],
      "tile": "cholecystitis-diagnosis", "audience": "clinicians" },
    { "phrases": ["deauville score", "deauville 5 point score", "deauville criteria", "pet response lymphoma", "5 point scale lymphoma", "fdg pet lymphoma response", "metabolic response lymphoma"],
      "tile": "deauville-score", "audience": "clinicians" },
    { "phrases": ["jones criteria", "acute rheumatic fever", "rheumatic fever diagnosis", "revised jones criteria", "arf diagnosis", "rheumatic fever criteria", "2015 jones criteria"],
      "tile": "jones-criteria", "audience": "clinicians" },
    { "phrases": ["gold abe", "gold group", "copd group", "gold abe assessment", "copd abe group", "gold 2023 group", "which gold group", "copd group a b e", "gold abcd"],
      "tile": "gold-abe", "audience": "clinicians" },
    { "phrases": ["cdi severity", "clostridioides difficile severity", "severe c diff", "fulminant c diff", "c difficile classification", "idsa c diff severity", "is this c diff severe", "non-severe severe fulminant cdi"],
      "tile": "cdi-severity", "audience": "clinicians" },
    { "phrases": ["la grade", "los angeles classification", "la classification esophagitis", "erosive esophagitis grade", "esophagitis grade", "la grade esophagitis", "reflux esophagitis grade", "grade a b c d esophagitis"],
      "tile": "la-esophagitis", "audience": "clinicians" },
    { "phrases": ["ccs angina", "ccs class", "canadian cardiovascular society angina", "angina class", "angina grade", "ccs angina grade", "angina functional class", "ccs grade"],
      "tile": "ccs-angina", "audience": "clinicians" },
    { "phrases": ["clavien dindo", "surgical complication grade", "postoperative complication classification", "clavien classification", "grade surgical complication", "complication grade surgery", "clavien dindo grade"],
      "tile": "clavien-dindo", "audience": "clinicians" },
    { "phrases": ["hinchey", "hinchey classification", "hinchey stage", "diverticulitis stage", "perforated diverticulitis grade", "diverticulitis classification", "hinchey diverticulitis", "complicated diverticulitis stage"],
      "tile": "hinchey", "audience": "clinicians" },
    { "phrases": ["bi-rads", "birads", "breast imaging category", "birads category", "mammogram category", "breast imaging reporting", "bi-rads 4", "what does birads mean"],
      "tile": "bi-rads", "audience": "clinicians" },
    { "phrases": ["siewert", "siewert classification", "siewert type", "esophagogastric junction adenocarcinoma", "gej adenocarcinoma type", "aeg classification", "cardia cancer type", "gastroesophageal junction tumor type"],
      "tile": "siewert", "audience": "clinicians" },
    { "phrases": ["wexner", "wexner score", "cleveland clinic incontinence score", "fecal incontinence score", "ccfis", "bowel incontinence score", "wexner incontinence", "jorge wexner"],
      "tile": "wexner", "audience": "clinicians" },
    { "phrases": ["lung-rads", "lungrads", "lung screening category", "lung nodule category", "lung cancer screening ct category", "lung-rads 4a", "ldct nodule follow up"],
      "tile": "lung-rads", "audience": "clinicians" },
    { "phrases": ["o-rads", "orads", "ovarian adnexal risk", "ovarian mass risk category", "adnexal mass ultrasound category", "ovarian cyst risk category", "o-rads ultrasound", "ovarian adnexal reporting"],
      "tile": "o-rads", "audience": "clinicians" },
    { "phrases": ["li-rads", "lirads", "liver imaging category", "liver observation category", "lr-5", "hcc imaging category", "liver imaging reporting", "li-rads category"],
      "tile": "li-rads", "audience": "clinicians" },
    { "phrases": ["montreal classification", "montreal ibd", "crohn phenotype", "montreal crohn", "ulcerative colitis extent", "ibd phenotype", "montreal classification crohn", "uc extent severity"],
      "tile": "montreal-ibd", "audience": "clinicians" },
    { "phrases": ["paris classification", "paris endoscopic classification", "polyp morphology", "superficial lesion morphology", "paris type", "sessile pedunculated flat depressed", "0-iic", "endoscopic lesion type"],
      "tile": "paris-classification", "audience": "clinicians" },
    { "phrases": ["nottingham prognostic index", "npi breast", "breast cancer prognosis", "nottingham index", "npi score breast", "breast cancer prognostic score", "nottingham prognostic", "breast npi"],
      "tile": "nottingham-prognostic-index", "audience": "clinicians" },
    { "phrases": ["fitzpatrick", "fitzpatrick skin type", "skin phototype", "skin type scale", "phototype", "fitzpatrick scale", "skin type i to vi", "sun reactive skin type"],
      "tile": "fitzpatrick-skin-type", "audience": "clinicians" },
    { "phrases": ["haggitt", "haggitt level", "haggitt classification", "malignant polyp invasion", "polyp invasion level", "invasive polyp level", "malignant colorectal polyp", "haggitt line"],
      "tile": "haggitt-level", "audience": "clinicians" },
    { "phrases": ["kikuchi", "kikuchi level", "kikuchi classification", "submucosal invasion depth", "sm1 sm2 sm3", "sessile polyp invasion", "submucosal invasion level", "sessile colorectal cancer invasion"],
      "tile": "kikuchi-level", "audience": "clinicians" },
    { "phrases": ["kudo", "kudo pit pattern", "pit pattern", "pit pattern classification", "colorectal pit pattern", "magnifying endoscopy pit", "crypt pattern colon", "chromoendoscopy pit pattern"],
      "tile": "kudo-pit-pattern", "audience": "clinicians" },
    { "phrases": ["nice classification", "nice nbi", "nbi polyp classification", "narrow band imaging polyp", "nbi international colorectal endoscopic", "nice type", "nbi colorectal classification", "optical diagnosis polyp nbi"],
      "tile": "nice-classification", "audience": "clinicians" },
    { "phrases": ["jnet", "jnet classification", "japan nbi expert team", "magnifying nbi classification", "jnet type", "nbi magnifying colorectal", "type 2b lesion", "japan nbi colorectal"],
      "tile": "jnet-classification", "audience": "clinicians" },
    { "phrases": ["outerbridge", "outerbridge classification", "chondromalacia grade", "cartilage grade", "articular cartilage damage", "chondral lesion grade", "cartilage lesion classification", "arthroscopy cartilage grade"],
      "tile": "outerbridge-cartilage", "audience": "clinicians" },
    { "phrases": ["icrs", "icrs grade", "icrs classification", "international cartilage repair society", "icrs cartilage grade", "cartilage repair society grade", "icrs cartilage lesion", "cartilage defect depth grade"],
      "tile": "icrs-cartilage", "audience": "clinicians" },
    { "phrases": ["cormack lehane", "cormack", "laryngoscopy grade", "laryngeal view grade", "cormack lehane grade", "glottic view classification", "laryngoscopy view", "intubation view grade"],
      "tile": "cormack-lehane", "audience": "clinicians" },
    { "phrases": ["clark level", "clark", "melanoma invasion level", "melanoma clark level", "anatomic level of invasion", "melanoma dermal invasion", "clark staging melanoma", "level of dermal invasion"],
      "tile": "clark-level", "audience": "clinicians" },
    { "phrases": ["mason classification", "mason", "radial head fracture type", "mason radial head", "radial head fracture classification", "mason johnston", "elbow radial head fracture grade", "fracture of the head of the radius classification"],
      "tile": "mason-radial-head", "audience": "clinicians" },
    { "phrases": ["hawkins classification", "hawkins talar", "talar neck fracture type", "talus fracture classification", "hawkins talus", "talar neck fracture classification", "hawkins canale", "talar avn risk classification"],
      "tile": "hawkins-talar", "audience": "clinicians" },
    { "phrases": ["sanders classification", "sanders", "calcaneal fracture type", "calcaneus fracture classification", "sanders calcaneal", "heel bone fracture classification", "calcaneal fracture ct classification", "sanders ct classification"],
      "tile": "sanders-calcaneal", "audience": "clinicians" },
    { "phrases": ["ficat classification", "ficat arlet", "avascular necrosis staging hip", "femoral head avn stage", "ficat staging", "osteonecrosis femoral head staging", "avn hip stage", "ficat arlet staging"],
      "tile": "ficat-arlet", "audience": "clinicians" },
    { "phrases": ["lichtman classification", "lichtman staging", "kienbock disease stage", "kienbock staging", "lunate osteonecrosis stage", "lunate avn stage", "kienbock classification", "lichtman kienbock"],
      "tile": "lichtman-kienbock", "audience": "clinicians" },
    { "phrases": ["catterall classification", "catterall", "perthes disease group", "legg calve perthes classification", "catterall perthes", "perthes classification", "perthes group", "capital femoral epiphysis involvement perthes"],
      "tile": "catterall-perthes", "audience": "clinicians" },
    { "phrases": ["herring classification", "herring", "lateral pillar perthes", "lateral pillar classification", "herring lateral pillar", "perthes lateral pillar group", "herring perthes", "lateral pillar height perthes"],
      "tile": "herring-pillar", "audience": "clinicians" },
    { "phrases": ["strasberg classification", "strasberg", "bile duct injury type", "bile duct injury classification", "biliary injury classification", "strasberg bismuth", "cholecystectomy bile duct injury grade", "bile duct injury grade"],
      "tile": "strasberg-bdi", "audience": "clinicians" },
    { "phrases": ["fazekas scale", "fazekas", "white matter hyperintensity grade", "white matter hyperintensities grade", "periventricular white matter grade", "deep white matter hyperintensity", "wmh grade", "small vessel disease mri grade"],
      "tile": "fazekas-wmh", "audience": "clinicians" },
    { "phrases": ["tscherne classification", "tscherne", "oestern tscherne", "closed fracture soft tissue grade", "closed fracture soft tissue injury", "soft tissue injury grade closed fracture", "tscherne grade", "closed fracture grade"],
      "tile": "tscherne-closed", "audience": "clinicians" },
    { "phrases": ["goligher classification", "goligher", "goligher grade", "internal hemorrhoid grade", "internal hemorrhoid grading", "hemorrhoid grade", "hemorrhoid grading", "hemorrhoid classification", "haemorrhoid grade", "grade of hemorrhoids"],
      "tile": "goligher-hemorrhoids", "audience": "clinicians" },
    { "phrases": ["lansky score", "lansky", "lansky play performance scale", "lansky performance", "pediatric performance status", "paediatric performance status", "pediatric karnofsky", "child performance status", "play performance scale"],
      "tile": "lansky", "audience": "clinicians" },
    { "phrases": ["crowe classification", "crowe", "crowe grade", "hip dysplasia grade", "hip dysplasia classification", "ddh grade", "ddh classification", "developmental dysplasia hip grade", "adult hip dysplasia grade"],
      "tile": "crowe-ddh", "audience": "clinicians" },
    { "phrases": ["tonnis grade", "tonnis classification", "tonnis classification hip", "tonnis osteoarthritis", "hip osteoarthritis grade", "hip oa grade", "radiographic hip osteoarthritis grade", "tonnis hip"],
      "tile": "tonnis-hip-oa", "audience": "clinicians" },
    { "phrases": ["lachman test grade", "lachman grade", "lachman test", "acl laxity grade", "acl laxity", "anterior cruciate ligament laxity", "acl tear grade", "knee laxity grade", "anterior tibial translation grade"],
      "tile": "lachman-acl", "audience": "clinicians" },
    { "phrases": ["ceap classification", "ceap", "ceap clinical class", "ceap class", "chronic venous disease class", "chronic venous insufficiency class", "venous disease classification", "varicose vein classification", "c0 c6 venous"],
      "tile": "ceap-venous", "audience": "clinicians" },
    { "phrases": ["nyha class", "nyha", "nyha classification", "new york heart association class", "heart failure functional class", "heart failure class", "functional class heart failure", "nyha functional class"],
      "tile": "nyha-class", "audience": "clinicians" },
    { "phrases": ["ramsay sedation scale", "ramsay", "ramsay score", "ramsay level", "ramsay sedation", "ramsay scale", "ramsay sedation score"],
      "tile": "ramsay-sedation", "audience": "clinicians" },
    { "phrases": ["pressure injury stage", "pressure injury staging", "pressure ulcer stage", "pressure ulcer staging", "npiap stage", "npuap stage", "bedsore stage", "decubitus ulcer stage", "stage 3 pressure injury", "unstageable pressure injury", "deep tissue pressure injury"],
      "tile": "pressure-injury-stage", "audience": "clinicians" },
    { "phrases": ["keith wagener barker", "hypertensive retinopathy grade", "hypertensive retinopathy classification", "kwb grade", "kwb classification", "hypertensive retinopathy staging", "retinopathy hypertension grade"],
      "tile": "kwb-retinopathy", "audience": "clinicians" },
    { "phrases": ["tanner stage", "tanner staging", "tanner scale", "sexual maturity rating", "smr stage", "puberty stage", "pubertal staging", "breast tanner stage", "genital tanner stage", "pubic hair tanner stage"],
      "tile": "tanner-staging", "audience": "clinicians" },
    { "phrases": ["forrester classification", "forrester", "forrester subset", "hemodynamic subset", "hemodynamic classification", "forrester hemodynamic", "warm and wet", "cold and wet", "cardiac index pcwp subset"],
      "tile": "forrester-hemodynamic", "audience": "clinicians" },
    { "phrases": ["shaffer grade", "shaffer grading", "shaffer angle", "gonioscopy angle grade", "gonioscopy grading", "anterior chamber angle grade", "angle grade glaucoma", "shaffer gonioscopy"],
      "tile": "shaffer-angle", "audience": "clinicians" },
    { "phrases": ["clinical activity score", "cas thyroid eye", "cas ted", "thyroid eye disease activity", "graves orbitopathy activity", "graves ophthalmopathy activity", "thyroid eye activity score", "ted activity score"],
      "tile": "cas-ted", "audience": "clinicians" },
    { "phrases": ["prague criteria", "prague c m", "prague classification", "barrett esophagus length", "barrett esophagus extent", "barrett grading", "prague barrett", "c and m barrett"],
      "tile": "prague-barrett", "audience": "clinicians" }
  ]
}
